ezca/__init__.py
ezca/__version__.py
ezca/cached.py
ezca/const.py
ezca/errors.py
ezca/ezca.py
ezca/ezcaPV.py
ezca/ligofilter.py
ezca/ramp.py
ezca/test_ezca.py
ezca/emulators/TEST_FILTER.adl
ezca/emulators/__init__.py
ezca/emulators/const.py
ezca/emulators/ligofilter.py
ezca-1.5.0.dist-info/COPYING
ezca-1.5.0.dist-info/COPYING-GPL-3
ezca-1.5.0.dist-info/METADATA
ezca-1.5.0.dist-info/WHEEL
ezca-1.5.0.dist-info/top_level.txt
ezca-1.5.0.dist-info/RECORD
