Metadata-Version: 2.1
Name: ezca
Version: 1.5.0
Summary: aLIGO CDS Python EPICS interface
Home-page: https://git.ligo.org/cds/python-ezca
Author: Jameson Graef Rollins
Author-email: jameson.rollins@ligo.org
License: GPL-3.0-or-later
Classifier: License :: OSI Approved :: GNU General Public License v3 or later (GPLv3+)
Classifier: Development Status :: 5 - Production/Stable
Classifier: Natural Language :: English
Classifier: Operating System :: OS Independent
Classifier: Programming Language :: Python
Classifier: Programming Language :: Python :: 3.7
Classifier: Programming Language :: Python :: 3.8
Classifier: Programming Language :: Python :: 3.9
Classifier: Programming Language :: Python :: 3.10
License-File: COPYING
License-File: COPYING-GPL-3
Requires-Dist: pcaspy
Requires-Dist: pyepics (>=3.4.1)
